[
 {
  "name": "",
  "model": [
   ""
  ]
 },
 {
  "name": "ACURA",
  "model": [
   "",
   "SLX",
   "ZDX",
   "RL",
   "CSX",
   "TL",
   "TSX",
   "EL",
   "Vigor",
   "Integra",
   "Legend",
   "RLX",
   "RSX",
   "Integra",
   "Legenda"
  ]
 },
 {
  "name": "ALFA ROMEO",
  "model": [
   "",
   "147",
   "156",
   "159",
   "164",
   "166",
   "75",
   "Brera",
   "Crosswagon Q4",
   "Giulia",
   "Giulietta",
   "GT",
   "GTV",
   "Mito",
   "Spider",
   "Stelvio"
  ]
 },
 {
  "name": "ASTON MARTIN",
  "model": [
   "",
   "AR1",
   "Cygnet",
   "DB",
   "DB7",
   "DB9",
   "DBS",
   "Lagonda",
   "Rapide",
   "Vanquish",
   "Vantage",
   "Virage",
   "Volante",
   "Zagato"
  ]
 },
 {
  "name": "AUDI",
  "model": [
   "",
   "100",
   "200",
   "5000",
   "80",
   "90",
   "A1",
   "A2",
   "A3",
   "A4",
   "A4 ALLROAD",
   "A5",
   "A5 SPORTBACK",
   "A6",
   "A6 ALLROAD",
   "A7 SPORTBACK",
   "A8"
  ]
 },
 {
  "name": "BENTLEY",
  "model": [
   ""
  ]
 },
 {
  "name": "BMW",
  "model": [
   "",
   "320",
   "330"
  ]
 },
 {
  "name": "BUGATTI",
  "model": [
   ""
  ]
 },
 {
  "name": "BUICK",
  "model": []
 },
 {
  "name": "CADILLAC",
  "model": []
 },
 {
  "name": "CHEVROLET",
  "model": []
 },
 {
  "name": "CITROËN",
  "model": []
 },
 {
  "name": "CHRYSLER",
  "model": []
 },
 {
  "name": "DACIA",
  "model": []
 },
 {
  "name": "DAIHATSU",
  "model": []
 },
 {
  "name": "DATSUN",
  "model": []
 },
 {
  "name": "DMC",
  "model": []
 },
 {
  "name": "DODGE",
  "model": []
 },
 {
  "name": "DONGFENG",
  "model": []
 },
 {
  "name": "EMGRAND",
  "model": []
 },
 {
  "name": "ENGLON",
  "model": []
 },
 {
  "name": "ETERNITI",
  "model": []
 },
 {
  "name": "FERRARI",
  "model": []
 },
 {
  "name": "FIAT",
  "model": []
 },
 {
  "name": "FORD",
  "model": []
 },
 {
  "name": "GENESIS",
  "model": []
 },
 {
  "name": "GMC",
  "model": []
 },
 {
  "name": "HENNESSEY",
  "model": []
 },
 {
  "name": "HOLDEN",
  "model": []
 },
 {
  "name": "HONDA",
  "model": []
 },
 {
  "name": "HYUNDAI",
  "model": []
 },
 {
  "name": "IMPERIA",
  "model": []
 },
 {
  "name": "INFINITI",
  "model": []
 },
 {
  "name": "JAC",
  "model": []
 },
 {
  "name": "JAGUAR",
  "model": []
 },
 {
  "name": "JEEP",
  "model": []
 },
 {
  "name": "KARMA",
  "model": []
 },
 {
  "name": "KOENIGSEGG",
  "model": []
 },
 {
  "name": "KIA",
  "model": []
 },
 {
  "name": "LADA",
  "model": []
 },
 {
  "name": "LAMBORGHINI",
  "model": []
 },
 {
  "name": "LANCIA",
  "model": []
 },
 {
  "name": "LAND ROVER",
  "model": []
 },
 {
  "name": "LANDWIND",
  "model": []
 },
 {
  "name": "LEBLANC",
  "model": []
 },
 {
  "name": "LEOPARD",
  "model": []
 },
 {
  "name": "LEXUS",
  "model": []
 },
 {
  "name": "LI-ION",
  "model": []
 },
 {
  "name": "LINCOLN",
  "model": []
 },
 {
  "name": "LOTEC",
  "model": []
 },
 {
  "name": "LOTUS CARS",
  "model": []
 },
 {
  "name": "LUXGEN",
  "model": []
 },
 {
  "name": "MARUTI SUZUKI",
  "model": []
 },
 {
  "name": "MASERATI",
  "model": []
 },
 {
  "name": "MAZDA",
  "model": []
 },
 {
  "name": "MCLAREN",
  "model": []
 },
 {
  "name": "MERCEDES-BENZ",
  "model": []
 },
 {
  "name": "MG",
  "model": []
 },
 {
  "name": "MICRO",
  "model": []
 },
 {
  "name": "MINI",
  "model": []
 },
 {
  "name": "MITSUBISHI",
  "model": []
 },
 {
  "name": "NISSAN",
  "model": []
 },
 {
  "name": "OPEL",
  "model": []
 },
 {
  "name": "ORCA",
  "model": []
 },
 {
  "name": "PAGANI",
  "model": []
 },
 {
  "name": "PEUGEOT",
  "model": []
 },
 {
  "name": "PORSCHE",
  "model": []
 },
 {
  "name": "RENAULT",
  "model": []
 },
 {
  "name": "ROLLS-ROYCE",
  "model": []
 },
 {
  "name": "ROVER",
  "model": []
 },
 {
  "name": "SAAB",
  "model": []
 },
 {
  "name": "SEAT",
  "model": []
 },
 {
  "name": "ŠKODA",
  "model": []
 },
 {
  "name": "SMART",
  "model": []
 },
 {
  "name": "SUBARU",
  "model": []
 },
 {
  "name": "SUZUKI",
  "model": []
 },
 {
  "name": "TESLA",
  "model": []
 },
 {
  "name": "TOYOTA",
  "model": []
 },
 {
  "name": "VOLKSWAGEN",
  "model": []
 },
 {
  "name": "VOLVO",
  "model": []
 },
 {
  "name": "ZAZ",
  "model": []
 }
]